fastmcts/__init__.py
fastmcts/utils.py
fastmcts/games/__init__.py
fastmcts/games/common.py
fastmcts/games/connect4.py
fastmcts/games/tictactoe.py
fastmcts/games/tictactoe2.py
fastmcts/tree/__init__.py
fastmcts/tree/nodes.py
fastmcts/tree/search.py
fastmcts-0.3.0.dist-info/LICENSE
fastmcts-0.3.0.dist-info/METADATA
fastmcts-0.3.0.dist-info/WHEEL
fastmcts-0.3.0.dist-info/top_level.txt
fastmcts-0.3.0.dist-info/RECORD
