Metadata-Version: 2.1
Name: fastmcts
Version: 0.3.0
Summary: Fast Python implementation of Monte Carlo Tree Search with parallel capabilities
Home-page: https://github.com/ttong-ai/fastmcts
Author: Tony Tong
License: MIT
Keywords: mcts monte carlo tree search parallel fast
Classifier: Programming Language :: Python :: 3
Classifier: Programming Language :: Python :: 3.8
Classifier: Programming Language :: Python :: 3.9
Classifier: Programming Language :: Python :: 3.10
Classifier: License :: OSI Approved :: MIT License
Classifier: Operating System :: OS Independent
Requires-Python: >=3.8
License-File: LICENSE
Requires-Dist: numpy <2.0,>=1.21
Provides-Extra: dev
Requires-Dist: pytest ; extra == 'dev'
Requires-Dist: black ; extra == 'dev'
